orbitron/__init__.py
orbitron/multimodal_rag.py
orbitron/embeddings/__init__.py
orbitron/embeddings/base.py
orbitron/embeddings/cohere.py
orbitron/models/__init__.py
orbitron/models/result.py
orbitron/utils/__init__.py
orbitron/utils/image_processing.py
orbitron/utils/logging.py
orbitron/utils/pdf_processing.py
orbitron/utils/utils.py
orbitron/vectorstores/__init__.py
orbitron/vectorstores/base.py
orbitron/vectorstores/qdrant.py
orbitron-0.1.0a1.dist-info/licenses/LICENSE
orbitron-0.1.0a1.dist-info/METADATA
orbitron-0.1.0a1.dist-info/WHEEL
orbitron-0.1.0a1.dist-info/top_level.txt
orbitron-0.1.0a1.dist-info/RECORD
