Metadata-Version: 2.4
Name: orbitron
Version: 0.1.0a1
Summary: A lightweight async package for building Multi-Modal RAG applications
Author-email: Aasher Kamal <aasherkamal786@gmail.com>
License: MIT
Project-URL: Homepage, https://github.com/aasherkamal216/orbitron
Project-URL: Issues, https://github.com/aasherkamal216/orbitron/issues
Requires-Python: >=3.11
License-File: LICENSE
Requires-Dist: pdf2image>=1.17.0
Requires-Dist: pillow>=11.2.1
Requires-Dist: python-dotenv>=1.1.0
Requires-Dist: qdrant-client>=1.14.2
Requires-Dist: numpy>=1.24.0
Requires-Dist: cohere>=5.15.0
Provides-Extra: dev
Requires-Dist: pytest>=7.0.0; extra == "dev"
Requires-Dist: pytest-asyncio>=0.18.0; extra == "dev"
Requires-Dist: black>=23.0.0; extra == "dev"
Requires-Dist: isort>=5.10.0; extra == "dev"
Requires-Dist: mypy>=1.0.0; extra == "dev"
Dynamic: license-file
